README.rst
setup.py
yamb/__init__.py
yamb.egg-info/PKG-INFO
yamb.egg-info/SOURCES.txt
yamb.egg-info/dependency_links.txt
yamb.egg-info/requires.txt
yamb.egg-info/top_level.txt