Metadata-Version: 1.1
Name: yamb
Version: 0.1.2
Summary: Lightweight test data generation framework
Home-page: UNKNOWN
Author: Ivan Kalinin
Author-email: pupssman@yandex-team.ru
License: Apache License, Version 2.0
Platform: UNKNOWN
Classifier: Intended Audience :: Developers
Classifier: License :: OSI Approved :: Apache Software License
Classifier: Operating System :: OS Independent
Classifier: Programming Language :: Python
Classifier: Topic :: Software Development
